{
  "agent": "agent-c-digest-writer",
  "timestamp": "2025-11-21T21:06:53.206948",
  "status": "completed",
  "data": {
    "digest": {
      "title": "Market Analysis Digest",
      "subtitle": "Market Update \u2022 November 21, 2025",
      "generated_at": "2025-11-21T21:06:53.206863",
      "summary": {
        "headline": "Daily Market Snapshot",
        "content": "**Market Headline:** \"Crypto Faces Bearish Pressure While Tech Stocks Rally Amid Economic Optimism\"\n\n**Executive Summary:** The cryptocurrency market is currently experiencing a significant downturn, with major players like Bitcoin and Ethereum suffering notable losses due to inflation concerns and regulatory scrutiny. In contrast, the stock market shows resilience, particularly within the technology sector, driven by strong earnings and positive investor sentiment. As we navigate these contrasting trends, potential consolidation in crypto may offer opportunities for cautious investors.\n\n**Key Opportunity to Watch:** Look for potential buy signals in the tech sector as strong earnings continue to drive stock prices, especially in companies like NVIDIA and Apple.\n\n**Key Risk to Monitor:** Keep an eye on regulatory developments in the cryptocurrency market, as new regulations could exacerbate the current bearish sentiment and lead to further declines in digital asset valuations.",
        "stats": {
          "total_crypto_market_cap": "$2.65T",
          "crypto_24h_avg_change": "-3.22%",
          "indices_avg_change": "+1.03%",
          "market_sentiment": {
            "label": "Bearish",
            "emoji": "\ud83d\udcc9",
            "color": "orange"
          }
        }
      },
      "crypto_section": {
        "title": "\ud83d\udc8e Cryptocurrency Market",
        "items": [
          {
            "symbol": "BTC",
            "name": "Bitcoin",
            "price": 84423,
            "price_formatted": "$84,423.00",
            "market_cap": 1687693614637,
            "market_cap_formatted": "$1.69T",
            "change_24h": -2.4569,
            "change_24h_formatted": "-2.46%",
            "change_7d": -11.76586950318014,
            "change_7d_formatted": "-11.77%",
            "rank": 1,
            "image": "https://coin-images.coingecko.com/coins/images/1/large/bitcoin.png?1696501400",
            "is_gaining": false
          },
          {
            "symbol": "ETH",
            "name": "Ethereum",
            "price": 2735.19,
            "price_formatted": "$2,735.19",
            "market_cap": 330594820777,
            "market_cap_formatted": "$330.59B",
            "change_24h": -3.80451,
            "change_24h_formatted": "-3.80%",
            "change_7d": -12.615223348480567,
            "change_7d_formatted": "-12.62%",
            "rank": 2,
            "image": "https://coin-images.coingecko.com/coins/images/279/large/ethereum.png?1696501628",
            "is_gaining": false
          },
          {
            "symbol": "USDT",
            "name": "Tether",
            "price": 0.999408,
            "price_formatted": "$0.9994",
            "market_cap": 184659888039,
            "market_cap_formatted": "$184.66B",
            "change_24h": 0.07171,
            "change_24h_formatted": "+0.07%",
            "change_7d": 0.010043041513219565,
            "change_7d_formatted": "+0.01%",
            "rank": 3,
            "image": "https://coin-images.coingecko.com/coins/images/325/large/Tether.png?1696501661",
            "is_gaining": true
          },
          {
            "symbol": "XRP",
            "name": "XRP",
            "price": 1.94,
            "price_formatted": "$1.94",
            "market_cap": 117116827537,
            "market_cap_formatted": "$117.12B",
            "change_24h": -3.44168,
            "change_24h_formatted": "-3.44%",
            "change_7d": -15.970789969182993,
            "change_7d_formatted": "-15.97%",
            "rank": 4,
            "image": "https://coin-images.coingecko.com/coins/images/44/large/xrp-symbol-white-128.png?1696501442",
            "is_gaining": false
          },
          {
            "symbol": "BNB",
            "name": "BNB",
            "price": 821.79,
            "price_formatted": "$821.79",
            "market_cap": 113445261429,
            "market_cap_formatted": "$113.45B",
            "change_24h": -6.1293,
            "change_24h_formatted": "-6.13%",
            "change_7d": -10.479063286800363,
            "change_7d_formatted": "-10.48%",
            "rank": 5,
            "image": "https://coin-images.coingecko.com/coins/images/825/large/bnb-icon2_2x.png?1696501970",
            "is_gaining": false
          }
        ],
        "analysis": "The current market sentiment is predominantly bearish, as evidenced by the significant declines across major cryptocurrencies, with Bitcoin down 2.46% in the last 24 hours and 11.77% over the past week. Notable trends include the continued downturn for Ethereum and XRP, both experiencing over 3% losses in the last day and over 15% in the last week, suggesting a broader market correction. Key movers, such as Bitcoin and Ethereum, are likely affected by macroeconomic factors, including inflation concerns and regulatory scrutiny, which have dampened investor confidence. Looking ahead, if the bearish trend persists, we may see further downward pressure, but potential support levels could mitigate extreme losses, prompting a possible consolidation phase.",
        "top_performers": [
          {
            "symbol": "USDT",
            "name": "Tether",
            "change_24h": 0.07171
          },
          {
            "symbol": "USDC",
            "name": "USDC",
            "change_24h": 0.00994
          },
          {
            "symbol": "TRX",
            "name": "TRON",
            "change_24h": -0.72983
          }
        ],
        "top_losers": [
          {
            "symbol": "DOGE",
            "name": "Dogecoin",
            "change_24h": -7.1399
          },
          {
            "symbol": "BNB",
            "name": "BNB",
            "change_24h": -6.1293
          },
          {
            "symbol": "SOL",
            "name": "Solana",
            "change_24h": -4.93541
          }
        ]
      },
      "stocks_section": {
        "title": "\ud83d\udcca Stock Market",
        "indices": [
          {
            "symbol": "SPY",
            "name": "S&P 500",
            "price": 587.5,
            "price_formatted": "$587.50",
            "change": 5.25,
            "change_formatted": "+5.25",
            "change_percent": 0.9,
            "change_percent_formatted": "+0.90%",
            "is_gaining": true
          },
          {
            "symbol": "QQQ",
            "name": "NASDAQ",
            "price": 505.75,
            "price_formatted": "$505.75",
            "change": 8.5,
            "change_formatted": "+8.50",
            "change_percent": 1.71,
            "change_percent_formatted": "+1.71%",
            "is_gaining": true
          },
          {
            "symbol": "DIA",
            "name": "Dow Jones",
            "price": 438.25,
            "price_formatted": "$438.25",
            "change": 2.1,
            "change_formatted": "+2.10",
            "change_percent": 0.48,
            "change_percent_formatted": "+0.48%",
            "is_gaining": true
          }
        ],
        "stocks": [
          {
            "symbol": "AAPL",
            "price": 228.5,
            "price_formatted": "$228.50",
            "change": 3.25,
            "change_formatted": "+3.25",
            "change_percent": 1.44,
            "change_percent_formatted": "+1.44%",
            "volume": 52000000,
            "volume_formatted": "$52.00M",
            "is_gaining": true
          },
          {
            "symbol": "MSFT",
            "price": 425.75,
            "price_formatted": "$425.75",
            "change": 5.5,
            "change_formatted": "+5.50",
            "change_percent": 1.31,
            "change_percent_formatted": "+1.31%",
            "volume": 28000000,
            "volume_formatted": "$28.00M",
            "is_gaining": true
          },
          {
            "symbol": "GOOGL",
            "price": 178.25,
            "price_formatted": "$178.25",
            "change": 2.75,
            "change_formatted": "+2.75",
            "change_percent": 1.57,
            "change_percent_formatted": "+1.57%",
            "volume": 22000000,
            "volume_formatted": "$22.00M",
            "is_gaining": true
          },
          {
            "symbol": "NVDA",
            "price": 148.5,
            "price_formatted": "$148.50",
            "change": 8.25,
            "change_formatted": "+8.25",
            "change_percent": 5.88,
            "change_percent_formatted": "+5.88%",
            "volume": 385000000,
            "volume_formatted": "$385.00M",
            "is_gaining": true
          },
          {
            "symbol": "TSLA",
            "price": 352.75,
            "price_formatted": "$352.75",
            "change": -5.25,
            "change_formatted": "-5.25",
            "change_percent": -1.47,
            "change_percent_formatted": "-1.47%",
            "volume": 95000000,
            "volume_formatted": "$95.00M",
            "is_gaining": false
          }
        ],
        "analysis": "The overall market sentiment appears positive today, as evidenced by gains across major indices, with the NASDAQ leading the way at +1.71%. Notably, the technology sector is driving this momentum, highlighted by NVIDIA's impressive +5.88% surge, alongside solid performances from Apple, Microsoft, and Alphabet, indicating strong investor interest in tech stocks. Key market drivers include robust earnings reports from tech companies and ongoing investor optimism regarding economic resilience, despite potential headwinds from inflation concerns. Looking ahead, the trading outlook remains cautiously optimistic, with potential volatility as traders react to upcoming economic data and earnings reports.",
        "market_direction": "strongly_bullish",
        "top_gainers": [
          {
            "symbol": "NVDA",
            "change_percent": 5.88
          },
          {
            "symbol": "GOOGL",
            "change_percent": 1.57
          },
          {
            "symbol": "AAPL",
            "change_percent": 1.44
          }
        ],
        "top_decliners": [
          {
            "symbol": "TSLA",
            "change_percent": -1.47
          },
          {
            "symbol": "MSFT",
            "change_percent": 1.31
          },
          {
            "symbol": "AAPL",
            "change_percent": 1.44
          }
        ]
      },
      "highlights": {
        "biggest_crypto_mover": {
          "symbol": "DOGE",
          "name": "Dogecoin",
          "change": -7.1399,
          "change_formatted": "-7.14%",
          "direction": "down"
        },
        "biggest_stock_mover": {
          "symbol": "NVDA",
          "change": 5.88,
          "change_formatted": "+5.88%",
          "direction": "up"
        },
        "market_leader": {
          "name": "NASDAQ",
          "symbol": "QQQ",
          "change": 1.71,
          "change_formatted": "+1.71%"
        }
      },
      "metadata": {
        "assets_tracked": 15,
        "indices_tracked": 3,
        "last_updated": "2025-11-21T21:06:53.206945"
      }
    }
  },
  "costs": {
    "total_usd": 0.0
  }
}