{
  "agent": "agent-b-market-analyzer",
  "timestamp": "2025-11-22T09:06:46.821057",
  "status": "completed",
  "data": {
    "crypto_analysis": {
      "analysis": "The current cryptocurrency market sentiment is predominantly bearish, as evidenced by the declining prices across major assets over the past week, with Bitcoin and Ethereum both down over 12%. Notable trends include a consistent decrease in market capitalization for top cryptocurrencies, suggesting a lack of buying pressure and potential profit-taking among investors. Key movers such as XRP and BNB are experiencing significant losses, possibly due to negative market sentiment and regulatory uncertainties impacting investor confidence. Looking ahead, unless there are catalysts for recovery, such as positive developments in adoption or regulatory clarity, the market may continue to face downward pressure in the short term.",
      "tokens_used": {
        "input": 277,
        "output": 119
      },
      "top_performers": [
        {
          "symbol": "BTC",
          "name": "Bitcoin",
          "change_24h": 0.28179
        },
        {
          "symbol": "USDT",
          "name": "Tether",
          "change_24h": 0.0416
        },
        {
          "symbol": "USDC",
          "name": "USDC",
          "change_24h": 0.00986
        }
      ],
      "top_losers": [
        {
          "symbol": "DOGE",
          "name": "Dogecoin",
          "change_24h": -3.40763
        },
        {
          "symbol": "BNB",
          "name": "BNB",
          "change_24h": -2.06202
        },
        {
          "symbol": "SOL",
          "name": "Solana",
          "change_24h": -1.84956
        }
      ]
    },
    "stock_analysis": {
      "analysis": "The overall market sentiment appears bullish, as indicated by positive movements in major indices, particularly the NASDAQ, which has risen by 1.71%. Notably, the technology sector is leading the charge, with NVDA showing a remarkable gain of 5.88%, suggesting strong investor interest in semiconductor stocks, likely driven by ongoing advancements in AI and cloud computing. Conversely, TSLA's decline of 1.47% may reflect concerns over production challenges or competitive pressures in the electric vehicle market. Looking ahead, trading sentiment could remain positive if economic indicators continue to show resilience, but caution is warranted given potential volatility from upcoming earnings reports and geopolitical developments.",
      "tokens_used": {
        "input": 191,
        "output": 131
      },
      "market_direction": "strongly_bullish",
      "top_gainers": [
        {
          "symbol": "NVDA",
          "change_percent": 5.88
        },
        {
          "symbol": "GOOGL",
          "change_percent": 1.57
        },
        {
          "symbol": "AAPL",
          "change_percent": 1.44
        }
      ],
      "top_decliners": [
        {
          "symbol": "TSLA",
          "change_percent": -1.47
        },
        {
          "symbol": "MSFT",
          "change_percent": 1.31
        },
        {
          "symbol": "AAPL",
          "change_percent": 1.44
        }
      ]
    },
    "market_summary": {
      "summary": "**Market Headline:** Diverging Trends: Cryptocurrency Faces Bearish Pressure While Stocks, Led by Tech, Rally Bullishly\n\n**Executive Summary:** The cryptocurrency market is currently experiencing a bearish sentiment, with major assets like Bitcoin and Ethereum down over 12% amid regulatory uncertainties and profit-taking. In contrast, the stock market is buoyed by positive momentum in major indices, particularly the technology sector, which is benefiting from advancements in AI and cloud computing. This divergence highlights the need for investors to navigate carefully between the two markets.\n\n**Key Opportunity to Watch:** Monitor potential rebounds in the technology sector, particularly in semiconductor stocks, as ongoing advancements in AI and cloud computing could drive further gains.\n\n**Key Risk to Monitor:** Keep an eye on regulatory developments impacting the cryptocurrency market, as negative news could exacerbate bearish sentiment and lead to further declines in asset prices.",
      "tokens_used": {
        "input": 350,
        "output": 171
      }
    },
    "analyzed_assets": {
      "crypto": 10,
      "stocks": 5,
      "indices": 3
    }
  },
  "tokens_used": {
    "input": 818,
    "output": 421
  }
}